Workbook

Sheet Логика цен
A1: ЛОГИКА ЦЕНООБРАЗОВАНИЯ — ключевые параметры (жёлтые ячейки редактируешь ты)
A3: Наценка B2B на РАЗОВЫЕ заявки (без подписки) | B3: 0.3 | C3: Безнал = налоги, счета-фактуры, акты, договор, SLA. Разово юрик платит ДОРОЖЕ физика
A4: Наценка за аварийный/ночной вызов | B4: 0.5 | C4: После 20:00, выходные, праздники: +50%; глубокая ночь — можно +100%
A5: Минимальный чек выезда B2C, сум | B5: 100000 | C5: Ниже — заявка убыточна с учётом дороги и доли мастера
A6: Доля мастера от стоимости работ | B6: 0.55 | C6: Коридор 50–60%. Материалы в долю не входят — по чеку
A7: Плановый техосмотр B2B (за один), сум | B7: 300000 | C7: Входит в подписку, база расчёта тарифов
A8: Скидка подписки от цены «B2B разовая» | B8: 0.1 | C8: Подписчик платит на 10% меньше РАЗОВОЙ B2B-цены того же объёма (≈ B2C × 1,17). Дороже розницы физика: скидка юрику — от юрика, не от физика
A9: Ставка НДС (Узбекистан) | B9: 0.12 | C9: Цены каталога — КОНЕЧНЫЕ (с НДС). В счёт-фактуре НДС выделяется изнутри: без НДС = цена / 1,12. Для клиентов-неплательщиков цена та же.
A10: Наценка «Срочно» — платный приоритет клиента | B10: 0.3 | C10: Тариф «Срочно»: +30% только к работам (ТЗ 17.3). Аварийная/ночная/срочная наценки взаимоисключающие — применяется одна наибольшая (ТЗ 3.7). Снимается автоматически, если работы не начаты за 3 ч (правило честности).
A11: ЦЕНОВАЯ ЛОГИКА (три уровня):
A12: 1. B2C — базовый прайс. Оплата Payme/Click/Uzum или карта. Гарантия 30 дней.
A13: 2. B2B разовая = B2C × (1 + наценка) — и «от», и «до» (сейчас +30%). Перечисление, СФ с выделением НДС, договор.
A14: 3. B2B абонентка: фикс. сумма в договоре; работы списываются по подписным ценам = «B2B разовая» × (1 − скидка 10%) ≈ B2C × 1,17. Осмотры входят.
A15: Всё сверх абонентки — отдельная счёт-фактура по ценам «B2B разовая» (+30%). Осмотры входят в абонентку.
A16: Продающий аргумент: «подписка — на 10% дешевле разовых вызовов + SLA + осмотры включены». Розница физика — отдельный мир, юрику недоступна.
A18: ПРАВИЛА ПРАЙСА:
A19: • Цена за РАБОТУ. Материалы отдельно, по чеку, без наценки мастера.
A20: • Цена называется клиенту ДО начала работ. Выход за диапазон — только через диспетчера.
A21: • Выезд + диагностика — по каталогу (позиция 1), при заказе работ — бесплатно.
A22: • Диапазон «от–до»: «от» — типовой случай, «до» — сложный (бетон, высота, демонтаж, старые коммуникации).
A24: НАСКОЛЬКО ДОРОЖЕ/ДЕШЕВЛЕ ДЛЯ БИЗНЕСА (считается формулами):
A25: B2B разовая vs B2C | B25: =B3 | C25: Разово бизнес платит дороже физлица на наценку B3
A26: Подписка vs B2C | B26: =(1+B3)*(1-B8)-1 | C26: Подписка ДОРОЖЕ розницы физика (~+17%), но дешевле разовой юрика
A27: B2B разовая vs подписка (клин продаж) | B27: =1/(1-B8)-1 | C27: Настолько разовая дороже подписной цены — аргумент в подписку

Sheet Каталог услуг
A1: ПОЛНЫЙ КАТАЛОГ УСЛУГ — B2C база, B2B разовая (+30%, с НДС и без), подписка (разовая −10%), доля мастера (Ташкент, июль 2026)
A2: Синие ячейки (B2C от/до, столбцы D–E) калибруешь ты. Остальные — формулы через «Логику цен»: B2B раз. = B2C × (1+B3); без НДС = с НДС / (1+B9); подписка = B2B раз. × (1−B8); мастеру = B2C × B6. Цены конечные (с НДС), в СФ НДС выделяется изнутри. Колонки N–R (нормо-часы, skill-теги, оборудование/парная/этапная) обязательны для импорта в платформу (DEV-02 PriceItem, планировщик слотов ТЗ 17.3) — заполняет владелец, см. DEV-05 п.17.
A4: № | B4: Услуга | C4: Ед. изм. | D4: B2C от (сум) | E4: B2C до (сум) | F4: B2B раз. от (с НДС) | G4: B2B раз. до (с НДС) | H4: B2B раз. от (без НДС) | I4: B2B раз. до (без НДС) | J4: Подписка от (с НДС) | K4: Подписка до (с НДС) | L4: Мастеру от (сум) | M4: Примечание | N4: Нормо-часы | O4: Skill-теги | P4: Требует оборудование (да/нет) | Q4: Парная (да/нет) | R4: Этапная (да/нет)
A5: ВЫЕЗД И ДИАГНОСТИКА
A6: 1 | B6: Выезд мастера + диагностика (бесплатно при заказе работ) | C6: выезд | D6: 150000 | E6: 200000 | F6: =ROUND(D6*(1+'Логика цен'!$B$3),-3) | G6: =ROUND(E6*(1+'Логика цен'!$B$3),-3) | H6: =ROUND(F6/(1+'Логика цен'!$B$9),-3) | I6: =ROUND(G6/(1+'Логика цен'!$B$9),-3) | J6: =ROUND(D6*(1+'Логика цен'!$B$3)*(1-'Логика цен'!$B$8),-3) | K6: =ROUND(E6*(1+'Логика цен'!$B$3)*(1-'Логика цен'!$B$8),-3) | L6: =ROUND(D6*'Логика цен'!$B$6,-3)
A7: 2 | B7: Аварийный выезд (вечер/ночь/выходные) | C7: выезд | D7: 200000 | E7: 250000 | F7: =ROUND(D7*(1+'Логика цен'!$B$3),-3) | G7: =ROUND(E7*(1+'Логика цен'!$B$3),-3) | H7: =ROUND(F7/(1+'Логика цен'!$B$9),-3) | I7: =ROUND(G7/(1+'Логика цен'!$B$9),-3) | J7: =ROUND(D7*(1+'Логика цен'!$B$3)*(1-'Логика цен'!$B$8),-3) | K7: =ROUND(E7*(1+'Логика цен'!$B$3)*(1-'Логика цен'!$B$8),-3) | L7: =ROUND(D7*'Логика цен'!$B$6,-3) | M7: Плюс наценка к работам по коэффициенту
A8: 3 | B8: Технический осмотр помещения по чек-листу | C8: объект | D8: 200000 | E8: 400000 | F8: =ROUND(D8*(1+'Логика цен'!$B$3),-3) | G8: =ROUND(E8*(1+'Логика цен'!$B$3),-3) | H8: =ROUND(F8/(1+'Логика цен'!$B$9),-3) | I8: =ROUND(G8/(1+'Логика цен'!$B$9),-3) | J8: =ROUND(D8*(1+'Логика цен'!$B$3)*(1-'Логика цен'!$B$8),-3) | K8: =ROUND(E8*(1+'Логика цен'!$B$3)*(1-'Логика цен'!$B$8),-3) | L8: =ROUND(D8*'Логика цен'!$B$6,-3) | M8: Для B2B входит в подписку
A9: 4 | B9: Составление дефектной ведомости / сметы работ | C9: объект | D9: 150000 | E9: 300000 | F9: =ROUND(D9*(1+'Логика цен'!$B$3),-3) | G9: =ROUND(E9*(1+'Логика цен'!$B$3),-3) | H9: =ROUND(F9/(1+'Логика цен'!$B$9),-3) | I9: =ROUND(G9/(1+'Логика цен'!$B$9),-3) | J9: =ROUND(D9*(1+'Логика цен'!$B$3)*(1-'Логика цен'!$B$8),-3) | K9: =ROUND(E9*(1+'Логика цен'!$B$3)*(1-'Логика цен'!$B$8),-3) | L9: =ROUND(D9*'Логика цен'!$B$6,-3) | M9: Бесплатно при заказе работ от 1 млн
A10: САНТЕХНИКА
A11: 5 | B11: Установка/замена смесителя | C11: шт | D11: 160000 | E11: 250000 | F11: =ROUND(D11*(1+'Логика цен'!$B$3),-3) | G11: =ROUND(E11*(1+'Логика цен'!$B$3),-3) | H11: =ROUND(F11/(1+'Логика цен'!$B$9),-3) | I11: =ROUND(G11/(1+'Логика цен'!$B$9),-3) | J11: =ROUND(D11*(1+'Логика цен'!$B$3)*(1-'Логика цен'!$B$8),-3) | K11: =ROUND(E11*(1+'Логика цен'!$B$3)*(1-'Логика цен'!$B$8),-3) | L11: =ROUND(D11*'Логика цен'!$B$6,-3)
A12: 6 | B12: Ремонт смесителя (картридж, кран-букса, течь) | C12: шт | D12: 90000 | E12: 150000 | F12: =ROUND(D12*(1+'Логика цен'!$B$3),-3) | G12: =ROUND(E12*(1+'Логика цен'!$B$3),-3) | H12: =ROUND(F12/(1+'Логика цен'!$B$9),-3) | I12: =ROUND(G12/(1+'Логика цен'!$B$9),-3) | J12: =ROUND(D12*(1+'Логика цен'!$B$3)*(1-'Логика цен'!$B$8),-3) | K12: =ROUND(E12*(1+'Логика цен'!$B$3)*(1-'Логика цен'!$B$8),-3) | L12: =ROUND(D12*'Логика цен'!$B$6,-3)
A13: 7 | B13: Установка/замена унитаза | C13: шт | D13: 250000 | E13: 400000 | F13: =ROUND(D13*(1+'Логика цен'!$B$3),-3) | G13: =ROUND(E13*(1+'Логика цен'!$B$3),-3) | H13: =ROUND(F13/(1+'Логика цен'!$B$9),-3) | I13: =ROUND(G13/(1+'Логика цен'!$B$9),-3) | J13: =ROUND(D13*(1+'Логика цен'!$B$3)*(1-'Логика цен'!$B$8),-3) | K13: =ROUND(E13*(1+'Логика цен'!$B$3)*(1-'Логика цен'!$B$8),-3) | L13: =ROUND(D13*'Логика цен'!$B$6,-3) | M13: С демонтажом старого
A14: 8 | B14: Замена арматуры/ремонт бачка | C14: шт | D14: 100000 | E14: 150000 | F14: =ROUND(D14*(1+'Логика цен'!$B$3),-3) | G14: =ROUND(E14*(1+'Логика цен'!$B$3),-3) | H14: =ROUND(F14/(1+'Логика цен'!$B$9),-3) | I14: =ROUND(G14/(1+'Логика цен'!$B$9),-3) | J14: =ROUND(D14*(1+'Логика цен'!$B$3)*(1-'Логика цен'!$B$8),-3) | K14: =ROUND(E14*(1+'Логика цен'!$B$3)*(1-'Логика цен'!$B$8),-3) | L14: =ROUND(D14*'Логика цен'!$B$6,-3)
A15: 9 | B15: Установка инсталляции (подвесной унитаз) | C15: шт | D15: 500000 | E15: 800000 | F15: =ROUND(D15*(1+'Логика цен'!$B$3),-3) | G15: =ROUND(E15*(1+'Логика цен'!$B$3),-3) | H15: =ROUND(F15/(1+'Логика цен'!$B$9),-3) | I15: =ROUND(G15/(1+'Логика цен'!$B$9),-3) | J15: =ROUND(D15*(1+'Логика цен'!$B$3)*(1-'Логика цен'!$B$8),-3) | K15: =ROUND(E15*(1+'Логика цен'!$B$3)*(1-'Логика цен'!$B$8),-3) | L15: =ROUND(D15*'Логика цен'!$B$6,-3)
A16: 10 | B16: Установка раковины/мойки/тюльпана | C16: шт | D16: 250000 | E16: 350000 | F16: =ROUND(D16*(1+'Логика цен'!$B$3),-3) | G16: =ROUND(E16*(1+'Логика цен'!$B$3),-3) | H16: =ROUND(F16/(1+'Логика цен'!$B$9),-3) | I16: =ROUND(G16/(1+'Логика цен'!$B$9),-3) | J16: =ROUND(D16*(1+'Логика цен'!$B$3)*(1-'Логика цен'!$B$8),-3) | K16: =ROUND(E16*(1+'Логика цен'!$B$3)*(1-'Логика цен'!$B$8),-3) | L16: =ROUND(D16*'Логика цен'!$B$6,-3) | M16: С сифоном
A17: 11 | B17: Установка ванны | C17: шт | D17: 400000 | E17: 700000 | F17: =ROUND(D17*(1+'Логика цен'!$B$3),-3) | G17: =ROUND(E17*(1+'Логика цен'!$B$3),-3) | H17: =ROUND(F17/(1+'Логика цен'!$B$9),-3) | I17: =ROUND(G17/(1+'Логика цен'!$B$9),-3) | J17: =ROUND(D17*(1+'Логика цен'!$B$3)*(1-'Логика цен'!$B$8),-3) | K17: =ROUND(E17*(1+'Логика цен'!$B$3)*(1-'Логика цен'!$B$8),-3) | L17: =ROUND(D17*'Логика цен'!$B$6,-3)
A18: 12 | B18: Установка душевой кабины | C18: шт | D18: 500000 | E18: 900000 | F18: =ROUND(D18*(1+'Логика цен'!$B$3),-3) | G18: =ROUND(E18*(1+'Логика цен'!$B$3),-3) | H18: =ROUND(F18/(1+'Логика цен'!$B$9),-3) | I18: =ROUND(G18/(1+'Логика цен'!$B$9),-3) | J18: =ROUND(D18*(1+'Логика цен'!$B$3)*(1-'Логика цен'!$B$8),-3) | K18: =ROUND(E18*(1+'Логика цен'!$B$3)*(1-'Логика цен'!$B$8),-3) | L18: =ROUND(D18*'Логика цен'!$B$6,-3) | M18: Сборка + подключение
A19: 13 | B19: Замена сифона | C19: шт | D19: 90000 | E19: 140000 | F19: =ROUND(D19*(1+'Логика цен'!$B$3),-3) | G19: =ROUND(E19*(1+'Логика цен'!$B$3),-3) | H19: =ROUND(F19/(1+'Логика цен'!$B$9),-3) | I19: =ROUND(G19/(1+'Логика цен'!$B$9),-3) | J19: =ROUND(D19*(1+'Логика цен'!$B$3)*(1-'Логика цен'!$B$8),-3) | K19: =ROUND(E19*(1+'Логика цен'!$B$3)*(1-'Логика цен'!$B$8),-3) | L19: =ROUND(D19*'Логика цен'!$B$6,-3)
A20: 14 | B20: Замена гибкой подводки | C20: шт | D20: 50000 | E20: 80000 | F20: =ROUND(D20*(1+'Логика цен'!$B$3),-3) | G20: =ROUND(E20*(1+'Логика цен'!$B$3),-3) | H20: =ROUND(F20/(1+'Логика цен'!$B$9),-3) | I20: =ROUND(G20/(1+'Логика цен'!$B$9),-3) | J20: =ROUND(D20*(1+'Логика цен'!$B$3)*(1-'Логика цен'!$B$8),-3) | K20: =ROUND(E20*(1+'Логика цен'!$B$3)*(1-'Логика цен'!$B$8),-3) | L20: =ROUND(D20*'Логика цен'!$B$6,-3)
A21: 15 | B21: Установка/замена шарового крана | C21: шт | D21: 120000 | E21: 150000 | F21: =ROUND(D21*(1+'Логика цен'!$B$3),-3) | G21: =ROUND(E21*(1+'Логика цен'!$B$3),-3) | H21: =ROUND(F21/(1+'Логика цен'!$B$9),-3) | I21: =ROUND(G21/(1+'Логика цен'!$B$9),-3) | J21: =ROUND(D21*(1+'Логика цен'!$B$3)*(1-'Логика цен'!$B$8),-3) | K21: =ROUND(E21*(1+'Логика цен'!$B$3)*(1-'Логика цен'!$B$8),-3) | L21: =ROUND(D21*'Логика цен'!$B$6,-3) | M21: Может требовать отключения стояка
A22: 16 | B22: Прочистка локального засора (раковина/ванна) | C22: точка | D22: 150000 | E22: 1000000 | F22: =ROUND(D22*(1+'Логика цен'!$B$3),-3) | G22: =ROUND(E22*(1+'Логика цен'!$B$3),-3) | H22: =ROUND(F22/(1+'Логика цен'!$B$9),-3) | I22: =ROUND(G22/(1+'Логика цен'!$B$9),-3) | J22: =ROUND(D22*(1+'Логика цен'!$B$3)*(1-'Логика цен'!$B$8),-3) | K22: =ROUND(E22*(1+'Логика цен'!$B$3)*(1-'Логика цен'!$B$8),-3) | L22: =ROUND(D22*'Логика цен'!$B$6,-3)
A23: 17 | B23: Прочистка канализации (стояк, трос до 10 м) | C23: точка | D23: 120000 | E23: 250000 | F23: =ROUND(D23*(1+'Логика цен'!$B$3),-3) | G23: =ROUND(E23*(1+'Логика цен'!$B$3),-3) | H23: =ROUND(F23/(1+'Логика цен'!$B$9),-3) | I23: =ROUND(G23/(1+'Логика цен'!$B$9),-3) | J23: =ROUND(D23*(1+'Логика цен'!$B$3)*(1-'Логика цен'!$B$8),-3) | K23: =ROUND(E23*(1+'Логика цен'!$B$3)*(1-'Логика цен'!$B$8),-3) | L23: =ROUND(D23*'Логика цен'!$B$6,-3)
A24: 18 | B24: Замена участка трубы водоснабжения (ППР, пайка) | C24: п.м | D24: 120000 | E24: 200000 | F24: =ROUND(D24*(1+'Логика цен'!$B$3),-3) | G24: =ROUND(E24*(1+'Логика цен'!$B$3),-3) | H24: =ROUND(F24/(1+'Логика цен'!$B$9),-3) | I24: =ROUND(G24/(1+'Логика цен'!$B$9),-3) | J24: =ROUND(D24*(1+'Логика цен'!$B$3)*(1-'Логика цен'!$B$8),-3) | K24: =ROUND(E24*(1+'Логика цен'!$B$3)*(1-'Логика цен'!$B$8),-3) | L24: =ROUND(D24*'Логика цен'!$B$6,-3)
A25: 19 | B25: Замена канализационной трубы | C25: п.м | D25: 100000 | E25: 280000 | F25: =ROUND(D25*(1+'Логика цен'!$B$3),-3) | G25: =ROUND(E25*(1+'Логика цен'!$B$3),-3) | H25: =ROUND(F25/(1+'Логика цен'!$B$9),-3) | I25: =ROUND(G25/(1+'Логика цен'!$B$9),-3) | J25: =ROUND(D25*(1+'Логика цен'!$B$3)*(1-'Логика цен'!$B$8),-3) | K25: =ROUND(E25*(1+'Логика цен'!$B$3)*(1-'Логика цен'!$B$8),-3) | L25: =ROUND(D25*'Логика цен'!$B$6,-3)
A26: 20 | B26: Врезка в существующую трубу (отвод) | C26: точка | D26: 120000 | E26: 250000 | F26: =ROUND(D26*(1+'Логика цен'!$B$3),-3) | G26: =ROUND(E26*(1+'Логика цен'!$B$3),-3) | H26: =ROUND(F26/(1+'Логика цен'!$B$9),-3) | I26: =ROUND(G26/(1+'Логика цен'!$B$9),-3) | J26: =ROUND(D26*(1+'Логика цен'!$B$3)*(1-'Логика цен'!$B$8),-3) | K26: =ROUND(E26*(1+'Логика цен'!$B$3)*(1-'Логика цен'!$B$8),-3) | L26: =ROUND(D26*'Логика цен'!$B$6,-3)
A27: 21 | B27: Установка фильтра воды / редуктора давления | C27: шт | D27: 100000 | E27: 200000 | F27: =ROUND(D27*(1+'Логика цен'!$B$3),-3) | G27: =ROUND(E27*(1+'Логика цен'!$B$3),-3) | H27: =ROUND(F27/(1+'Логика цен'!$B$9),-3) | I27: =ROUND(G27/(1+'Логика цен'!$B$9),-3) | J27: =ROUND(D27*(1+'Логика цен'!$B$3)*(1-'Логика цен'!$B$8),-3) | K27: =ROUND(E27*(1+'Логика цен'!$B$3)*(1-'Логика цен'!$B$8),-3) | L27: =ROUND(D27*'Логика цен'!$B$6,-3)
A28: 22 | B28: Установка счётчика воды (без опломбировки) | C28: шт | D28: 150000 | E28: 250000 | F28: =ROUND(D28*(1+'Логика цен'!$B$3),-3) | G28: =ROUND(E28*(1+'Логика цен'!$B$3),-3) | H28: =ROUND(F28/(1+'Логика цен'!$B$9),-3) | I28: =ROUND(G28/(1+'Логика цен'!$B$9),-3) | J28: =ROUND(D28*(1+'Логика цен'!$B$3)*(1-'Логика цен'!$B$8),-3) | K28: =ROUND(E28*(1+'Логика цен'!$B$3)*(1-'Логика цен'!$B$8),-3) | L28: =ROUND(D28*'Логика цен'!$B$6,-3) | M28: Опломбировка — через водоканал
A29: 23 | B29: Установка/замена радиатора отопления | C29: шт | D29: 300000 | E29: 500000 | F29: =ROUND(D29*(1+'Логика цен'!$B$3),-3) | G29: =ROUND(E29*(1+'Логика цен'!$B$3),-3) | H29: =ROUND(F29/(1+'Логика цен'!$B$9),-3) | I29: =ROUND(G29/(1+'Логика цен'!$B$9),-3) | J29: =ROUND(D29*(1+'Логика цен'!$B$3)*(1-'Логика цен'!$B$8),-3) | K29: =ROUND(E29*(1+'Логика цен'!$B$3)*(1-'Логика цен'!$B$8),-3) | L29: =ROUND(D29*'Логика цен'!$B$6,-3)
A30: 24 | B30: Промывка радиатора/системы отопления | C30: шт | D30: 250000 | E30: 450000 | F30: =ROUND(D30*(1+'Логика цен'!$B$3),-3) | G30: =ROUND(E30*(1+'Логика цен'!$B$3),-3) | H30: =ROUND(F30/(1+'Логика цен'!$B$9),-3) | I30: =ROUND(G30/(1+'Логика цен'!$B$9),-3) | J30: =ROUND(D30*(1+'Логика цен'!$B$3)*(1-'Логика цен'!$B$8),-3) | K30: =ROUND(E30*(1+'Логика цен'!$B$3)*(1-'Логика цен'!$B$8),-3) | L30: =ROUND(D30*'Логика цен'!$B$6,-3) | M30: Сезон: осень
A31: 25 | B31: Установка полотенцесушителя | C31: шт | D31: 250000 | E31: 450000 | F31: =ROUND(D31*(1+'Логика цен'!$B$3),-3) | G31: =ROUND(E31*(1+'Логика цен'!$B$3),-3) | H31: =ROUND(F31/(1+'Логика цен'!$B$9),-3) | I31: =ROUND(G31/(1+'Логика цен'!$B$9),-3) | J31: =ROUND(D31*(1+'Логика цен'!$B$3)*(1-'Логика цен'!$B$8),-3) | K31: =ROUND(E31*(1+'Логика цен'!$B$3)*(1-'Логика цен'!$B$8),-3) | L31: =ROUND(D31*'Логика цен'!$B$6,-3)
A32: 26 | B32: Установка водонагревателя | C32: шт | D32: 250000 | E32: 450000 | F32: =ROUND(D32*(1+'Логика цен'!$B$3),-3) | G32: =ROUND(E32*(1+'Логика цен'!$B$3),-3) | H32: =ROUND(F32/(1+'Логика цен'!$B$9),-3) | I32: =ROUND(G32/(1+'Логика цен'!$B$9),-3) | J32: =ROUND(D32*(1+'Логика цен'!$B$3)*(1-'Логика цен'!$B$8),-3) | K32: =ROUND(E32*(1+'Логика цен'!$B$3)*(1-'Логика цен'!$B$8),-3) | L32: =ROUND(D32*'Логика цен'!$B$6,-3)
A33: 27 | B33: Подключение стиральной/посудомоечной машины | C33: шт | D33: 150000 | E33: 350000 | F33: =ROUND(D33*(1+'Логика цен'!$B$3),-3) | G33: =ROUND(E33*(1+'Логика цен'!$B$3),-3) | H33: =ROUND(F33/(1+'Логика цен'!$B$9),-3) | I33: =ROUND(G33/(1+'Логика цен'!$B$9),-3) | J33: =ROUND(D33*(1+'Логика цен'!$B$3)*(1-'Логика цен'!$B$8),-3) | K33: =ROUND(E33*(1+'Логика цен'!$B$3)*(1-'Логика цен'!$B$8),-3) | L33: =ROUND(D33*'Логика цен'!$B$6,-3)
A34: 28 | B34: Герметизация ванны/душа/стыков | C34: п.м | D34: 20000 | E34: 70000 | F34: =ROUND(D34*(1+'Логика цен'!$B$3),-3) | G34: =ROUND(E34*(1+'Логика цен'!$B$3),-3) | H34: =ROUND(F34/(1+'Логика цен'!$B$9),-3) | I34: =ROUND(G34/(1+'Логика цен'!$B$9),-3) | J34: =ROUND(D34*(1+'Логика цен'!$B$3)*(1-'Логика цен'!$B$8),-3) | K34: =ROUND(E34*(1+'Логика цен'!$B$3)*(1-'Логика цен'!$B$8),-3) | L34: =ROUND(D34*'Логика цен'!$B$6,-3)
A35: ЭЛЕКТРИКА
A36: 29 | B36: Установка/замена розетки/выключателя (в готовое место) | C36: точка | D36: 70000 | E36: 150000 | F36: =ROUND(D36*(1+'Логика цен'!$B$3),-3) | G36: =ROUND(E36*(1+'Логика цен'!$B$3),-3) | H36: =ROUND(F36/(1+'Логика цен'!$B$9),-3) | I36: =ROUND(G36/(1+'Логика цен'!$B$9),-3) | J36: =ROUND(D36*(1+'Логика цен'!$B$3)*(1-'Логика цен'!$B$8),-3) | K36: =ROUND(E36*(1+'Логика цен'!$B$3)*(1-'Логика цен'!$B$8),-3) | L36: =ROUND(D36*'Логика цен'!$B$6,-3)
A37: 30 | B37: Перенос розетки/выключателя | C37: точка | D37: 150000 | E37: 550000 | F37: =ROUND(D37*(1+'Логика цен'!$B$3),-3) | G37: =ROUND(E37*(1+'Логика цен'!$B$3),-3) | H37: =ROUND(F37/(1+'Логика цен'!$B$9),-3) | I37: =ROUND(G37/(1+'Логика цен'!$B$9),-3) | J37: =ROUND(D37*(1+'Логика цен'!$B$3)*(1-'Логика цен'!$B$8),-3) | K37: =ROUND(E37*(1+'Логика цен'!$B$3)*(1-'Логика цен'!$B$8),-3) | L37: =ROUND(D37*'Логика цен'!$B$6,-3) | M37: Со штробой и кабелем 1м
A38: 31 | B38: Монтаж новой точки (подрозетник + штроба до 1 м) | C38: точка | D38: 150000 | E38: 280000 | F38: =ROUND(D38*(1+'Логика цен'!$B$3),-3) | G38: =ROUND(E38*(1+'Логика цен'!$B$3),-3) | H38: =ROUND(F38/(1+'Логика цен'!$B$9),-3) | I38: =ROUND(G38/(1+'Логика цен'!$B$9),-3) | J38: =ROUND(D38*(1+'Логика цен'!$B$3)*(1-'Логика цен'!$B$8),-3) | K38: =ROUND(E38*(1+'Логика цен'!$B$3)*(1-'Логика цен'!$B$8),-3) | L38: =ROUND(D38*'Логика цен'!$B$6,-3) | M38: Бетон дороже
A39: 32 | B39: Установка диммера/терморегулятора | C39: шт | D39: 90000 | E39: 180000 | F39: =ROUND(D39*(1+'Логика цен'!$B$3),-3) | G39: =ROUND(E39*(1+'Логика цен'!$B$3),-3) | H39: =ROUND(F39/(1+'Логика цен'!$B$9),-3) | I39: =ROUND(G39/(1+'Логика цен'!$B$9),-3) | J39: =ROUND(D39*(1+'Логика цен'!$B$3)*(1-'Логика цен'!$B$8),-3) | K39: =ROUND(E39*(1+'Логика цен'!$B$3)*(1-'Логика цен'!$B$8),-3) | L39: =ROUND(D39*'Логика цен'!$B$6,-3)
A40: 33 | B40: Установка люстры | C40: шт | D40: 200000 | E40: 350000 | F40: =ROUND(D40*(1+'Логика цен'!$B$3),-3) | G40: =ROUND(E40*(1+'Логика цен'!$B$3),-3) | H40: =ROUND(F40/(1+'Логика цен'!$B$9),-3) | I40: =ROUND(G40/(1+'Логика цен'!$B$9),-3) | J40: =ROUND(D40*(1+'Логика цен'!$B$3)*(1-'Логика цен'!$B$8),-3) | K40: =ROUND(E40*(1+'Логика цен'!$B$3)*(1-'Логика цен'!$B$8),-3) | L40: =ROUND(D40*'Логика цен'!$B$6,-3)
A41: 34 | B41: Установка люстры с монтажом крюка/планки в бетон | C41: шт | D41: 250000 | E41: 450000 | F41: =ROUND(D41*(1+'Логика цен'!$B$3),-3) | G41: =ROUND(E41*(1+'Логика цен'!$B$3),-3) | H41: =ROUND(F41/(1+'Логика цен'!$B$9),-3) | I41: =ROUND(G41/(1+'Логика цен'!$B$9),-3) | J41: =ROUND(D41*(1+'Логика цен'!$B$3)*(1-'Логика цен'!$B$8),-3) | K41: =ROUND(E41*(1+'Логика цен'!$B$3)*(1-'Логика цен'!$B$8),-3) | L41: =ROUND(D41*'Логика цен'!$B$6,-3)
A42: 35 | B42: Установка точечного светильника/бра/трека | C42: шт | D42: 150000 | E42: 290000 | F42: =ROUND(D42*(1+'Логика цен'!$B$3),-3) | G42: =ROUND(E42*(1+'Логика цен'!$B$3),-3) | H42: =ROUND(F42/(1+'Логика цен'!$B$9),-3) | I42: =ROUND(G42/(1+'Логика цен'!$B$9),-3) | J42: =ROUND(D42*(1+'Логика цен'!$B$3)*(1-'Логика цен'!$B$8),-3) | K42: =ROUND(E42*(1+'Логика цен'!$B$3)*(1-'Логика цен'!$B$8),-3) | L42: =ROUND(D42*'Логика цен'!$B$6,-3)
A43: 36 | B43: Установка LED-ленты с блоком питания | C43: п.м | D43: 100000 | E43: 370000 | F43: =ROUND(D43*(1+'Логика цен'!$B$3),-3) | G43: =ROUND(E43*(1+'Логика цен'!$B$3),-3) | H43: =ROUND(F43/(1+'Логика цен'!$B$9),-3) | I43: =ROUND(G43/(1+'Логика цен'!$B$9),-3) | J43: =ROUND(D43*(1+'Логика цен'!$B$3)*(1-'Логика цен'!$B$8),-3) | K43: =ROUND(E43*(1+'Логика цен'!$B$3)*(1-'Логика цен'!$B$8),-3) | L43: =ROUND(D43*'Логика цен'!$B$6,-3)
A44: 37 | B44: Установка датчика движения/фотореле | C44: шт | D44: 180000 | E44: 250000 | F44: =ROUND(D44*(1+'Логика цен'!$B$3),-3) | G44: =ROUND(E44*(1+'Логика цен'!$B$3),-3) | H44: =ROUND(F44/(1+'Логика цен'!$B$9),-3) | I44: =ROUND(G44/(1+'Логика цен'!$B$9),-3) | J44: =ROUND(D44*(1+'Логика цен'!$B$3)*(1-'Логика цен'!$B$8),-3) | K44: =ROUND(E44*(1+'Логика цен'!$B$3)*(1-'Логика цен'!$B$8),-3) | L44: =ROUND(D44*'Логика цен'!$B$6,-3)
A45: 38 | B45: Монтаж уличного освещения (светильник на фасад) | C45: шт | D45: 120000 | E45: 250000 | F45: =ROUND(D45*(1+'Логика цен'!$B$3),-3) | G45: =ROUND(E45*(1+'Логика цен'!$B$3),-3) | H45: =ROUND(F45/(1+'Логика цен'!$B$9),-3) | I45: =ROUND(G45/(1+'Логика цен'!$B$9),-3) | J45: =ROUND(D45*(1+'Логика цен'!$B$3)*(1-'Логика цен'!$B$8),-3) | K45: =ROUND(E45*(1+'Логика цен'!$B$3)*(1-'Логика цен'!$B$8),-3) | L45: =ROUND(D45*'Логика цен'!$B$6,-3)
A46: 39 | B46: Замена автомата/УЗО в щитке | C46: шт | D46: 90000 | E46: 190000 | F46: =ROUND(D46*(1+'Логика цен'!$B$3),-3) | G46: =ROUND(E46*(1+'Логика цен'!$B$3),-3) | H46: =ROUND(F46/(1+'Логика цен'!$B$9),-3) | I46: =ROUND(G46/(1+'Логика цен'!$B$9),-3) | J46: =ROUND(D46*(1+'Логика цен'!$B$3)*(1-'Логика цен'!$B$8),-3) | K46: =ROUND(E46*(1+'Логика цен'!$B$3)*(1-'Логика цен'!$B$8),-3) | L46: =ROUND(D46*'Логика цен'!$B$6,-3)
A47: 40 | B47: Установка реле напряжения | C47: шт | D47: 100000 | E47: 290000 | F47: =ROUND(D47*(1+'Логика цен'!$B$3),-3) | G47: =ROUND(E47*(1+'Логика цен'!$B$3),-3) | H47: =ROUND(F47/(1+'Логика цен'!$B$9),-3) | I47: =ROUND(G47/(1+'Логика цен'!$B$9),-3) | J47: =ROUND(D47*(1+'Логика цен'!$B$3)*(1-'Логика цен'!$B$8),-3) | K47: =ROUND(E47*(1+'Логика цен'!$B$3)*(1-'Логика цен'!$B$8),-3) | L47: =ROUND(D47*'Логика цен'!$B$6,-3) | M47: Актуально при скачках в сети
A48: 41 | B48: Сборка/ревизия электрощита (квартира) | C48: щит | D48: 300000 | E48: 1700000 | F48: =ROUND(D48*(1+'Логика цен'!$B$3),-3) | G48: =ROUND(E48*(1+'Логика цен'!$B$3),-3) | H48: =ROUND(F48/(1+'Логика цен'!$B$9),-3) | I48: =ROUND(G48/(1+'Логика цен'!$B$9),-3) | J48: =ROUND(D48*(1+'Логика цен'!$B$3)*(1-'Логика цен'!$B$8),-3) | K48: =ROUND(E48*(1+'Логика цен'!$B$3)*(1-'Логика цен'!$B$8),-3) | L48: =ROUND(D48*'Логика цен'!$B$6,-3)
A49: 42 | B49: Сборка электрощита (офис/коммерция) | C49: щит | D49: 700000 | E49: 2500000 | F49: =ROUND(D49*(1+'Логика цен'!$B$3),-3) | G49: =ROUND(E49*(1+'Логика цен'!$B$3),-3) | H49: =ROUND(F49/(1+'Логика цен'!$B$9),-3) | I49: =ROUND(G49/(1+'Логика цен'!$B$9),-3) | J49: =ROUND(D49*(1+'Логика цен'!$B$3)*(1-'Логика цен'!$B$8),-3) | K49: =ROUND(E49*(1+'Логика цен'!$B$3)*(1-'Логика цен'!$B$8),-3) | L49: =ROUND(D49*'Логика цен'!$B$6,-3)
A50: 43 | B50: Замена вводного кабеля (щиток—квартира) | C50: заявка | D50: 300000 | E50: 1600000 | F50: =ROUND(D50*(1+'Логика цен'!$B$3),-3) | G50: =ROUND(E50*(1+'Логика цен'!$B$3),-3) | H50: =ROUND(F50/(1+'Логика цен'!$B$9),-3) | I50: =ROUND(G50/(1+'Логика цен'!$B$9),-3) | J50: =ROUND(D50*(1+'Логика цен'!$B$3)*(1-'Логика цен'!$B$8),-3) | K50: =ROUND(E50*(1+'Логика цен'!$B$3)*(1-'Логика цен'!$B$8),-3) | L50: =ROUND(D50*'Логика цен'!$B$6,-3)
A51: 44 | B51: Поиск неисправности (КЗ, нет питания) | C51: заявка | D51: 100000 | E51: 250000 | F51: =ROUND(D51*(1+'Логика цен'!$B$3),-3) | G51: =ROUND(E51*(1+'Логика цен'!$B$3),-3) | H51: =ROUND(F51/(1+'Логика цен'!$B$9),-3) | I51: =ROUND(G51/(1+'Логика цен'!$B$9),-3) | J51: =ROUND(D51*(1+'Логика цен'!$B$3)*(1-'Логика цен'!$B$8),-3) | K51: =ROUND(E51*(1+'Логика цен'!$B$3)*(1-'Логика цен'!$B$8),-3) | L51: =ROUND(D51*'Логика цен'!$B$6,-3)
A52: 45 | B52: Прокладка кабеля открыто (кабель-канал) | C52: п.м | D52: 25000 | E52: 45000 | F52: =ROUND(D52*(1+'Логика цен'!$B$3),-3) | G52: =ROUND(E52*(1+'Логика цен'!$B$3),-3) | H52: =ROUND(F52/(1+'Логика цен'!$B$9),-3) | I52: =ROUND(G52/(1+'Логика цен'!$B$9),-3) | J52: =ROUND(D52*(1+'Логика цен'!$B$3)*(1-'Логика цен'!$B$8),-3) | K52: =ROUND(E52*(1+'Логика цен'!$B$3)*(1-'Логика цен'!$B$8),-3) | L52: =ROUND(D52*'Логика цен'!$B$6,-3)
A53: 46 | B53: Скрытая прокладка кабеля (в готовую штробу) | C53: п.м | D53: 20000 | E53: 35000 | F53: =ROUND(D53*(1+'Логика цен'!$B$3),-3) | G53: =ROUND(E53*(1+'Логика цен'!$B$3),-3) | H53: =ROUND(F53/(1+'Логика цен'!$B$9),-3) | I53: =ROUND(G53/(1+'Логика цен'!$B$9),-3) | J53: =ROUND(D53*(1+'Логика цен'!$B$3)*(1-'Логика цен'!$B$8),-3) | K53: =ROUND(E53*(1+'Логика цен'!$B$3)*(1-'Логика цен'!$B$8),-3) | L53: =ROUND(D53*'Логика цен'!$B$6,-3) | M53: Штроба — отдельно, см. раздел демонтажа
A54: 47 | B54: Подключение варочной панели/духовки | C54: шт | D54: 120000 | E54: 250000 | F54: =ROUND(D54*(1+'Логика цен'!$B$3),-3) | G54: =ROUND(E54*(1+'Логика цен'!$B$3),-3) | H54: =ROUND(F54/(1+'Логика цен'!$B$9),-3) | I54: =ROUND(G54/(1+'Логика цен'!$B$9),-3) | J54: =ROUND(D54*(1+'Логика цен'!$B$3)*(1-'Логика цен'!$B$8),-3) | K54: =ROUND(E54*(1+'Логика цен'!$B$3)*(1-'Логика цен'!$B$8),-3) | L54: =ROUND(D54*'Логика цен'!$B$6,-3)
A55: 48 | B55: Монтаж/подключение электрического тёплого пола | C55: м² | D55: 80000 | E55: 180000 | F55: =ROUND(D55*(1+'Логика цен'!$B$3),-3) | G55: =ROUND(E55*(1+'Логика цен'!$B$3),-3) | H55: =ROUND(F55/(1+'Логика цен'!$B$9),-3) | I55: =ROUND(G55/(1+'Логика цен'!$B$9),-3) | J55: =ROUND(D55*(1+'Логика цен'!$B$3)*(1-'Логика цен'!$B$8),-3) | K55: =ROUND(E55*(1+'Логика цен'!$B$3)*(1-'Логика цен'!$B$8),-3) | L55: =ROUND(D55*'Логика цен'!$B$6,-3) | M55: Без стяжки
A56: 49 | B56: Установка счётчика электроэнергии (без опломбировки) | C56: шт | D56: 250000 | E56: 350000 | F56: =ROUND(D56*(1+'Логика цен'!$B$3),-3) | G56: =ROUND(E56*(1+'Логика цен'!$B$3),-3) | H56: =ROUND(F56/(1+'Логика цен'!$B$9),-3) | I56: =ROUND(G56/(1+'Логика цен'!$B$9),-3) | J56: =ROUND(D56*(1+'Логика цен'!$B$3)*(1-'Логика цен'!$B$8),-3) | K56: =ROUND(E56*(1+'Логика цен'!$B$3)*(1-'Логика цен'!$B$8),-3) | L56: =ROUND(D56*'Логика цен'!$B$6,-3)
A57: 50 | B57: Монтаж заземления (контур для частного дома) | C57: объект | D57: 1800000 | E57: 3500000 | F57: =ROUND(D57*(1+'Логика цен'!$B$3),-3) | G57: =ROUND(E57*(1+'Логика цен'!$B$3),-3) | H57: =ROUND(F57/(1+'Логика цен'!$B$9),-3) | I57: =ROUND(G57/(1+'Логика цен'!$B$9),-3) | J57: =ROUND(D57*(1+'Логика цен'!$B$3)*(1-'Логика цен'!$B$8),-3) | K57: =ROUND(E57*(1+'Логика цен'!$B$3)*(1-'Логика цен'!$B$8),-3) | L57: =ROUND(D57*'Логика цен'!$B$6,-3) | M57: без учёта материала (металлополосы)
A58: 51 | B58: Установка стабилизатора напряжения | C58: шт | D58: 150000 | E58: 300000 | F58: =ROUND(D58*(1+'Логика цен'!$B$3),-3) | G58: =ROUND(E58*(1+'Логика цен'!$B$3),-3) | H58: =ROUND(F58/(1+'Логика цен'!$B$9),-3) | I58: =ROUND(G58/(1+'Логика цен'!$B$9),-3) | J58: =ROUND(D58*(1+'Логика цен'!$B$3)*(1-'Логика цен'!$B$8),-3) | K58: =ROUND(E58*(1+'Логика цен'!$B$3)*(1-'Логика цен'!$B$8),-3) | L58: =ROUND(D58*'Логика цен'!$B$6,-3)
A59: 52 | B59: Замена лампочки (разово) | C59: шт | D59: 20000 | E59: 40000 | F59: =ROUND(D59*(1+'Логика цен'!$B$3),-3) | G59: =ROUND(E59*(1+'Логика цен'!$B$3),-3) | H59: =ROUND(F59/(1+'Логика цен'!$B$9),-3) | I59: =ROUND(G59/(1+'Логика цен'!$B$9),-3) | J59: =ROUND(D59*(1+'Логика цен'!$B$3)*(1-'Логика цен'!$B$8),-3) | K59: =ROUND(E59*(1+'Логика цен'!$B$3)*(1-'Логика цен'!$B$8),-3) | L59: =ROUND(D59*'Логика цен'!$B$6,-3) | M59: Действует минимальный чек выезда — выгодно вместе с другими работами
A60: 53 | B60: Замена патрона/цоколя светильника | C60: шт | D60: 40000 | E60: 90000 | F60: =ROUND(D60*(1+'Логика цен'!$B$3),-3) | G60: =ROUND(E60*(1+'Логика цен'!$B$3),-3) | H60: =ROUND(F60/(1+'Логика цен'!$B$9),-3) | I60: =ROUND(G60/(1+'Логика цен'!$B$9),-3) | J60: =ROUND(D60*(1+'Логика цен'!$B$3)*(1-'Логика цен'!$B$8),-3) | K60: =ROUND(E60*(1+'Логика цен'!$B$3)*(1-'Логика цен'!$B$8),-3) | L60: =ROUND(D60*'Логика цен'!$B$6,-3)
A61: 54 | B61: Замена ламп/светильников (пакет, от 10 шт) | C61: шт | D61: 15000 | E61: 30000 | F61: =ROUND(D61*(1+'Логика цен'!$B$3),-3) | G61: =ROUND(E61*(1+'Логика цен'!$B$3),-3) | H61: =ROUND(F61/(1+'Логика цен'!$B$9),-3) | I61: =ROUND(G61/(1+'Логика цен'!$B$9),-3) | J61: =ROUND(D61*(1+'Логика цен'!$B$3)*(1-'Логика цен'!$B$8),-3) | K61: =ROUND(E61*(1+'Логика цен'!$B$3)*(1-'Логика цен'!$B$8),-3) | L61: =ROUND(D61*'Логика цен'!$B$6,-3) | M61: B2B: офисы, ТЦ — массовая замена
A62: ДЕМОНТАЖ, БУРЕНИЕ, ШТРОБЛЕНИЕ
A63: 55 | B63: Штроба в штукатурке/гипсе (до 20×20 мм) | C63: п.м | D63: 25000 | E63: 40000 | F63: =ROUND(D63*(1+'Логика цен'!$B$3),-3) | G63: =ROUND(E63*(1+'Логика цен'!$B$3),-3) | H63: =ROUND(F63/(1+'Логика цен'!$B$9),-3) | I63: =ROUND(G63/(1+'Логика цен'!$B$9),-3) | J63: =ROUND(D63*(1+'Логика цен'!$B$3)*(1-'Логика цен'!$B$8),-3) | K63: =ROUND(E63*(1+'Логика цен'!$B$3)*(1-'Логика цен'!$B$8),-3) | L63: =ROUND(D63*'Логика цен'!$B$6,-3)
A64: 56 | B64: Штроба в кирпиче | C64: п.м | D64: 40000 | E64: 60000 | F64: =ROUND(D64*(1+'Логика цен'!$B$3),-3) | G64: =ROUND(E64*(1+'Логика цен'!$B$3),-3) | H64: =ROUND(F64/(1+'Логика цен'!$B$9),-3) | I64: =ROUND(G64/(1+'Логика цен'!$B$9),-3) | J64: =ROUND(D64*(1+'Логика цен'!$B$3)*(1-'Логика цен'!$B$8),-3) | K64: =ROUND(E64*(1+'Логика цен'!$B$3)*(1-'Логика цен'!$B$8),-3) | L64: =ROUND(D64*'Логика цен'!$B$6,-3)
A65: 57 | B65: Штроба в бетоне | C65: п.м | D65: 60000 | E65: 100000 | F65: =ROUND(D65*(1+'Логика цен'!$B$3),-3) | G65: =ROUND(E65*(1+'Логика цен'!$B$3),-3) | H65: =ROUND(F65/(1+'Логика цен'!$B$9),-3) | I65: =ROUND(G65/(1+'Логика цен'!$B$9),-3) | J65: =ROUND(D65*(1+'Логика цен'!$B$3)*(1-'Логика цен'!$B$8),-3) | K65: =ROUND(E65*(1+'Логика цен'!$B$3)*(1-'Логика цен'!$B$8),-3) | L65: =ROUND(D65*'Логика цен'!$B$6,-3)
A66: 58 | B66: Отверстие перфоратором в кирпиче/гипсе (до 22 мм) | C66: шт | D66: 25000 | E66: 40000 | F66: =ROUND(D66*(1+'Логика цен'!$B$3),-3) | G66: =ROUND(E66*(1+'Логика цен'!$B$3),-3) | H66: =ROUND(F66/(1+'Логика цен'!$B$9),-3) | I66: =ROUND(G66/(1+'Логика цен'!$B$9),-3) | J66: =ROUND(D66*(1+'Логика цен'!$B$3)*(1-'Логика цен'!$B$8),-3) | K66: =ROUND(E66*(1+'Логика цен'!$B$3)*(1-'Логика цен'!$B$8),-3) | L66: =ROUND(D66*'Логика цен'!$B$6,-3)
A67: 59 | B67: Отверстие перфоратором в бетоне (до 22 мм) | C67: шт | D67: 45000 | E67: 70000 | F67: =ROUND(D67*(1+'Логика цен'!$B$3),-3) | G67: =ROUND(E67*(1+'Логика цен'!$B$3),-3) | H67: =ROUND(F67/(1+'Логика цен'!$B$9),-3) | I67: =ROUND(G67/(1+'Логика цен'!$B$9),-3) | J67: =ROUND(D67*(1+'Логика цен'!$B$3)*(1-'Логика цен'!$B$8),-3) | K67: =ROUND(E67*(1+'Логика цен'!$B$3)*(1-'Логика цен'!$B$8),-3) | L67: =ROUND(D67*'Логика цен'!$B$6,-3)
A68: 60 | B68: Сквозное отверстие под трассу кондиционера (до 50 мм) | C68: шт | D68: 280000 | E68: 450000 | F68: =ROUND(D68*(1+'Логика цен'!$B$3),-3) | G68: =ROUND(E68*(1+'Логика цен'!$B$3),-3) | H68: =ROUND(F68/(1+'Логика цен'!$B$9),-3) | I68: =ROUND(G68/(1+'Логика цен'!$B$9),-3) | J68: =ROUND(D68*(1+'Логика цен'!$B$3)*(1-'Логика цен'!$B$8),-3) | K68: =ROUND(E68*(1+'Логика цен'!$B$3)*(1-'Логика цен'!$B$8),-3) | L68: =ROUND(D68*'Логика цен'!$B$6,-3) | M68: Бетон/толщина стены
A69: 61 | B69: Алмазное бурение (под канализацию, 100–110 мм) | C69: шт | D69: 280000 | E69: 450000 | F69: =ROUND(D69*(1+'Логика цен'!$B$3),-3) | G69: =ROUND(E69*(1+'Логика цен'!$B$3),-3) | H69: =ROUND(F69/(1+'Логика цен'!$B$9),-3) | I69: =ROUND(G69/(1+'Логика цен'!$B$9),-3) | J69: =ROUND(D69*(1+'Логика цен'!$B$3)*(1-'Логика цен'!$B$8),-3) | K69: =ROUND(E69*(1+'Логика цен'!$B$3)*(1-'Логика цен'!$B$8),-3) | L69: =ROUND(D69*'Логика цен'!$B$6,-3)
A70: 62 | B70: Сверление кафеля/керамогранита (аккуратное) | C70: шт | D70: 30000 | E70: 40000 | F70: =ROUND(D70*(1+'Логика цен'!$B$3),-3) | G70: =ROUND(E70*(1+'Логика цен'!$B$3),-3) | H70: =ROUND(F70/(1+'Логика цен'!$B$9),-3) | I70: =ROUND(G70/(1+'Логика цен'!$B$9),-3) | J70: =ROUND(D70*(1+'Логика цен'!$B$3)*(1-'Логика цен'!$B$8),-3) | K70: =ROUND(E70*(1+'Логика цен'!$B$3)*(1-'Логика цен'!$B$8),-3) | L70: =ROUND(D70*'Логика цен'!$B$6,-3) | M70: цена указана за отверстие от 6-10мм
A71: 63 | B71: Демонтаж плитки | C71: м² | D71: 30000 | E71: 60000 | F71: =ROUND(D71*(1+'Логика цен'!$B$3),-3) | G71: =ROUND(E71*(1+'Логика цен'!$B$3),-3) | H71: =ROUND(F71/(1+'Логика цен'!$B$9),-3) | I71: =ROUND(G71/(1+'Логика цен'!$B$9),-3) | J71: =ROUND(D71*(1+'Логика цен'!$B$3)*(1-'Логика цен'!$B$8),-3) | K71: =ROUND(E71*(1+'Логика цен'!$B$3)*(1-'Логика цен'!$B$8),-3) | L71: =ROUND(D71*'Логика цен'!$B$6,-3)
A72: 64 | B72: Демонтаж сантехники (унитаз/ванна/раковина) | C72: шт | D72: 80000 | E72: 200000 | F72: =ROUND(D72*(1+'Логика цен'!$B$3),-3) | G72: =ROUND(E72*(1+'Логика цен'!$B$3),-3) | H72: =ROUND(F72/(1+'Логика цен'!$B$9),-3) | I72: =ROUND(G72/(1+'Логика цен'!$B$9),-3) | J72: =ROUND(D72*(1+'Логика цен'!$B$3)*(1-'Логика цен'!$B$8),-3) | K72: =ROUND(E72*(1+'Логика цен'!$B$3)*(1-'Логика цен'!$B$8),-3) | L72: =ROUND(D72*'Логика цен'!$B$6,-3) | M72: Чугунная ванна — верх диапазона
A73: 65 | B73: Демонтаж перегородки (гипсокартон) | C73: м² | D73: 20000 | E73: 50000 | F73: =ROUND(D73*(1+'Логика цен'!$B$3),-3) | G73: =ROUND(E73*(1+'Логика цен'!$B$3),-3) | H73: =ROUND(F73/(1+'Логика цен'!$B$9),-3) | I73: =ROUND(G73/(1+'Логика цен'!$B$9),-3) | J73: =ROUND(D73*(1+'Логика цен'!$B$3)*(1-'Логика цен'!$B$8),-3) | K73: =ROUND(E73*(1+'Логика цен'!$B$3)*(1-'Логика цен'!$B$8),-3) | L73: =ROUND(D73*'Логика цен'!$B$6,-3)
A74: 66 | B74: Снятие обоев/старой краски | C74: м² | D74: 25000 | E74: 40000 | F74: =ROUND(D74*(1+'Логика цен'!$B$3),-3) | G74: =ROUND(E74*(1+'Логика цен'!$B$3),-3) | H74: =ROUND(F74/(1+'Логика цен'!$B$9),-3) | I74: =ROUND(G74/(1+'Логика цен'!$B$9),-3) | J74: =ROUND(D74*(1+'Логика цен'!$B$3)*(1-'Логика цен'!$B$8),-3) | K74: =ROUND(E74*(1+'Логика цен'!$B$3)*(1-'Логика цен'!$B$8),-3) | L74: =ROUND(D74*'Логика цен'!$B$6,-3)
A75: 67 | B75: Вынос мусора после демонтажа | C75: заявка | D75: 300000 | E75: 450000 | F75: =ROUND(D75*(1+'Логика цен'!$B$3),-3) | G75: =ROUND(E75*(1+'Логика цен'!$B$3),-3) | H75: =ROUND(F75/(1+'Логика цен'!$B$9),-3) | I75: =ROUND(G75/(1+'Логика цен'!$B$9),-3) | J75: =ROUND(D75*(1+'Логика цен'!$B$3)*(1-'Логика цен'!$B$8),-3) | K75: =ROUND(E75*(1+'Логика цен'!$B$3)*(1-'Логика цен'!$B$8),-3) | L75: =ROUND(D75*'Логика цен'!$B$6,-3) | M75: До 10 мешков; больше — газель
A76: СВАРОЧНЫЕ РАБОТЫ
A77: 68 | B77: Сварка стальных труб (отопление/вода) | C77: стык | D77: 280000 | E77: 350000 | F77: =ROUND(D77*(1+'Логика цен'!$B$3),-3) | G77: =ROUND(E77*(1+'Логика цен'!$B$3),-3) | H77: =ROUND(F77/(1+'Логика цен'!$B$9),-3) | I77: =ROUND(G77/(1+'Логика цен'!$B$9),-3) | J77: =ROUND(D77*(1+'Логика цен'!$B$3)*(1-'Логика цен'!$B$8),-3) | K77: =ROUND(E77*(1+'Логика цен'!$B$3)*(1-'Логика цен'!$B$8),-3) | L77: =ROUND(D77*'Логика цен'!$B$6,-3)
A78: 69 | B78: Врезка в стальной стояк со сваркой | C78: точка | D78: 300000 | E78: 500000 | F78: =ROUND(D78*(1+'Логика цен'!$B$3),-3) | G78: =ROUND(E78*(1+'Логика цен'!$B$3),-3) | H78: =ROUND(F78/(1+'Логика цен'!$B$9),-3) | I78: =ROUND(G78/(1+'Логика цен'!$B$9),-3) | J78: =ROUND(D78*(1+'Логика цен'!$B$3)*(1-'Логика цен'!$B$8),-3) | K78: =ROUND(E78*(1+'Логика цен'!$B$3)*(1-'Логика цен'!$B$8),-3) | L78: =ROUND(D78*'Логика цен'!$B$6,-3) | M78: С согласованием отключения
A79: 70 | B79: Сварочные работы общие (металлоконструкции) | C79: час | D79: 250000 | E79: 350000 | F79: =ROUND(D79*(1+'Логика цен'!$B$3),-3) | G79: =ROUND(E79*(1+'Логика цен'!$B$3),-3) | H79: =ROUND(F79/(1+'Логика цен'!$B$9),-3) | I79: =ROUND(G79/(1+'Логика цен'!$B$9),-3) | J79: =ROUND(D79*(1+'Логика цен'!$B$3)*(1-'Логика цен'!$B$8),-3) | K79: =ROUND(E79*(1+'Логика цен'!$B$3)*(1-'Логика цен'!$B$8),-3) | L79: =ROUND(D79*'Логика цен'!$B$6,-3)
A80: 71 | B80: Ремонт ворот/калитки (петли, замок, полотно) | C80: заявка | D80: 200000 | E80: 500000 | F80: =ROUND(D80*(1+'Логика цен'!$B$3),-3) | G80: =ROUND(E80*(1+'Логика цен'!$B$3),-3) | H80: =ROUND(F80/(1+'Логика цен'!$B$9),-3) | I80: =ROUND(G80/(1+'Логика цен'!$B$9),-3) | J80: =ROUND(D80*(1+'Логика цен'!$B$3)*(1-'Логика цен'!$B$8),-3) | K80: =ROUND(E80*(1+'Логика цен'!$B$3)*(1-'Логика цен'!$B$8),-3) | L80: =ROUND(D80*'Логика цен'!$B$6,-3)
A81: 72 | B81: Изготовление и монтаж решётки на окно | C81: м² | D81: 300000 | E81: 600000 | F81: =ROUND(D81*(1+'Логика цен'!$B$3),-3) | G81: =ROUND(E81*(1+'Логика цен'!$B$3),-3) | H81: =ROUND(F81/(1+'Логика цен'!$B$9),-3) | I81: =ROUND(G81/(1+'Логика цен'!$B$9),-3) | J81: =ROUND(D81*(1+'Логика цен'!$B$3)*(1-'Логика цен'!$B$8),-3) | K81: =ROUND(E81*(1+'Логика цен'!$B$3)*(1-'Логика цен'!$B$8),-3) | L81: =ROUND(D81*'Логика цен'!$B$6,-3) | M81: Без стоимости металла
A82: 73 | B82: Монтаж навеса/козырька (простой) | C82: м² | D82: 200000 | E82: 400000 | F82: =ROUND(D82*(1+'Логика цен'!$B$3),-3) | G82: =ROUND(E82*(1+'Логика цен'!$B$3),-3) | H82: =ROUND(F82/(1+'Логика цен'!$B$9),-3) | I82: =ROUND(G82/(1+'Логика цен'!$B$9),-3) | J82: =ROUND(D82*(1+'Логика цен'!$B$3)*(1-'Логика цен'!$B$8),-3) | K82: =ROUND(E82*(1+'Логика цен'!$B$3)*(1-'Логика цен'!$B$8),-3) | L82: =ROUND(D82*'Логика цен'!$B$6,-3) | M82: Без стоимости материала
A83: 74 | B83: Сварка/усиление каркасов, стеллажей | C83: час | D83: 150000 | E83: 250000 | F83: =ROUND(D83*(1+'Логика цен'!$B$3),-3) | G83: =ROUND(E83*(1+'Логика цен'!$B$3),-3) | H83: =ROUND(F83/(1+'Логика цен'!$B$9),-3) | I83: =ROUND(G83/(1+'Логика цен'!$B$9),-3) | J83: =ROUND(D83*(1+'Логика цен'!$B$3)*(1-'Логика цен'!$B$8),-3) | K83: =ROUND(E83*(1+'Логика цен'!$B$3)*(1-'Логика цен'!$B$8),-3) | L83: =ROUND(D83*'Логика цен'!$B$6,-3)
A84: КОНДИЦИОНЕРЫ И ВЕНТИЛЯЦИЯ
A85: 75 | B85: Чистка кондиционера (профилактика, сплит) | C85: шт | D85: 250000 | E85: 450000 | F85: =ROUND(D85*(1+'Логика цен'!$B$3),-3) | G85: =ROUND(E85*(1+'Логика цен'!$B$3),-3) | H85: =ROUND(F85/(1+'Логика цен'!$B$9),-3) | I85: =ROUND(G85/(1+'Логика цен'!$B$9),-3) | J85: =ROUND(D85*(1+'Логика цен'!$B$3)*(1-'Логика цен'!$B$8),-3) | K85: =ROUND(E85*(1+'Логика цен'!$B$3)*(1-'Логика цен'!$B$8),-3) | L85: =ROUND(D85*'Логика цен'!$B$6,-3) | M85: Сезонный хит май–сентябрь
A86: 76 | B86: Заправка фреоном | C86: шт | D86: 200000 | E86: 400000 | F86: =ROUND(D86*(1+'Логика цен'!$B$3),-3) | G86: =ROUND(E86*(1+'Логика цен'!$B$3),-3) | H86: =ROUND(F86/(1+'Логика цен'!$B$9),-3) | I86: =ROUND(G86/(1+'Логика цен'!$B$9),-3) | J86: =ROUND(D86*(1+'Логика цен'!$B$3)*(1-'Логика цен'!$B$8),-3) | K86: =ROUND(E86*(1+'Логика цен'!$B$3)*(1-'Логика цен'!$B$8),-3) | L86: =ROUND(D86*'Логика цен'!$B$6,-3) | M86: Зависит от типа фреона
A87: 77 | B87: Установка сплит-системы (стандарт, до 3 м трассы) | C87: шт | D87: 500000 | E87: 900000 | F87: =ROUND(D87*(1+'Логика цен'!$B$3),-3) | G87: =ROUND(E87*(1+'Логика цен'!$B$3),-3) | H87: =ROUND(F87/(1+'Логика цен'!$B$9),-3) | I87: =ROUND(G87/(1+'Логика цен'!$B$9),-3) | J87: =ROUND(D87*(1+'Логика цен'!$B$3)*(1-'Логика цен'!$B$8),-3) | K87: =ROUND(E87*(1+'Логика цен'!$B$3)*(1-'Логика цен'!$B$8),-3) | L87: =ROUND(D87*'Логика цен'!$B$6,-3) | M87: Доп. трасса — за п.м
A88: 78 | B88: Дополнительная трасса кондиционера | C88: п.м | D88: 80000 | E88: 150000 | F88: =ROUND(D88*(1+'Логика цен'!$B$3),-3) | G88: =ROUND(E88*(1+'Логика цен'!$B$3),-3) | H88: =ROUND(F88/(1+'Логика цен'!$B$9),-3) | I88: =ROUND(G88/(1+'Логика цен'!$B$9),-3) | J88: =ROUND(D88*(1+'Логика цен'!$B$3)*(1-'Логика цен'!$B$8),-3) | K88: =ROUND(E88*(1+'Логика цен'!$B$3)*(1-'Логика цен'!$B$8),-3) | L88: =ROUND(D88*'Логика цен'!$B$6,-3)
A89: 79 | B89: Демонтаж кондиционера | C89: шт | D89: 250000 | E89: 400000 | F89: =ROUND(D89*(1+'Логика цен'!$B$3),-3) | G89: =ROUND(E89*(1+'Логика цен'!$B$3),-3) | H89: =ROUND(F89/(1+'Логика цен'!$B$9),-3) | I89: =ROUND(G89/(1+'Логика цен'!$B$9),-3) | J89: =ROUND(D89*(1+'Логика цен'!$B$3)*(1-'Логика цен'!$B$8),-3) | K89: =ROUND(E89*(1+'Логика цен'!$B$3)*(1-'Логика цен'!$B$8),-3) | L89: =ROUND(D89*'Логика цен'!$B$6,-3) | M89: внутренний "фен" \ наружный агрегат
A90: 80 | B90: Перенос кондиционера | C90: шт | D90: 500000 | E90: 1300000 | F90: =ROUND(D90*(1+'Логика цен'!$B$3),-3) | G90: =ROUND(E90*(1+'Логика цен'!$B$3),-3) | H90: =ROUND(F90/(1+'Логика цен'!$B$9),-3) | I90: =ROUND(G90/(1+'Логика цен'!$B$9),-3) | J90: =ROUND(D90*(1+'Логика цен'!$B$3)*(1-'Логика цен'!$B$8),-3) | K90: =ROUND(E90*(1+'Логика цен'!$B$3)*(1-'Логика цен'!$B$8),-3) | L90: =ROUND(D90*'Логика цен'!$B$6,-3) | M90: внутренний "фен" \ наружный агрегат
A91: 81 | B91: Диагностика/ремонт кондиционера | C91: заявка | D91: 150000 | E91: 400000 | F91: =ROUND(D91*(1+'Логика цен'!$B$3),-3) | G91: =ROUND(E91*(1+'Логика цен'!$B$3),-3) | H91: =ROUND(F91/(1+'Логика цен'!$B$9),-3) | I91: =ROUND(G91/(1+'Логика цен'!$B$9),-3) | J91: =ROUND(D91*(1+'Логика цен'!$B$3)*(1-'Логика цен'!$B$8),-3) | K91: =ROUND(E91*(1+'Логика цен'!$B$3)*(1-'Логика цен'!$B$8),-3) | L91: =ROUND(D91*'Логика цен'!$B$6,-3) | M91: Без запчастей
A92: 82 | B92: Чистка кухонной вытяжки (бытовой) | C92: шт | D92: 100000 | E92: 300000 | F92: =ROUND(D92*(1+'Логика цен'!$B$3),-3) | G92: =ROUND(E92*(1+'Логика цен'!$B$3),-3) | H92: =ROUND(F92/(1+'Логика цен'!$B$9),-3) | I92: =ROUND(G92/(1+'Логика цен'!$B$9),-3) | J92: =ROUND(D92*(1+'Логика цен'!$B$3)*(1-'Логика цен'!$B$8),-3) | K92: =ROUND(E92*(1+'Логика цен'!$B$3)*(1-'Логика цен'!$B$8),-3) | L92: =ROUND(D92*'Логика цен'!$B$6,-3) | M92: возможен хим.клининг
A93: 83 | B93: Установка вытяжного вентилятора (санузел) | C93: шт | D93: 100000 | E93: 180000 | F93: =ROUND(D93*(1+'Логика цен'!$B$3),-3) | G93: =ROUND(E93*(1+'Логика цен'!$B$3),-3) | H93: =ROUND(F93/(1+'Логика цен'!$B$9),-3) | I93: =ROUND(G93/(1+'Логика цен'!$B$9),-3) | J93: =ROUND(D93*(1+'Логика цен'!$B$3)*(1-'Логика цен'!$B$8),-3) | K93: =ROUND(E93*(1+'Логика цен'!$B$3)*(1-'Логика цен'!$B$8),-3) | L93: =ROUND(D93*'Логика цен'!$B$6,-3) | M93: без выреза и расширения отверстий
A94: 84 | B94: Обслуживание вентиляции (B2B: HoReCa) | C94: объект | D94: 500000 | E94: 1500000 | F94: =ROUND(D94*(1+'Логика цен'!$B$3),-3) | G94: =ROUND(E94*(1+'Логика цен'!$B$3),-3) | H94: =ROUND(F94/(1+'Логика цен'!$B$9),-3) | I94: =ROUND(G94/(1+'Логика цен'!$B$9),-3) | J94: =ROUND(D94*(1+'Логика цен'!$B$3)*(1-'Логика цен'!$B$8),-3) | K94: =ROUND(E94*(1+'Логика цен'!$B$3)*(1-'Логика цен'!$B$8),-3) | L94: =ROUND(D94*'Логика цен'!$B$6,-3) | M94: Критично для проверок
A95: БЫТОВАЯ ТЕХНИКА (мелкий ремонт)
A96: 85 | B96: Диагностика бытовой техники | C96: шт | D96: 80000 | E96: 120000 | F96: =ROUND(D96*(1+'Логика цен'!$B$3),-3) | G96: =ROUND(E96*(1+'Логика цен'!$B$3),-3) | H96: =ROUND(F96/(1+'Логика цен'!$B$9),-3) | I96: =ROUND(G96/(1+'Логика цен'!$B$9),-3) | J96: =ROUND(D96*(1+'Логика цен'!$B$3)*(1-'Логика цен'!$B$8),-3) | K96: =ROUND(E96*(1+'Логика цен'!$B$3)*(1-'Логика цен'!$B$8),-3) | L96: =ROUND(D96*'Логика цен'!$B$6,-3) | M96: Бесплатно при ремонте
A97: 86 | B97: Замена ТЭНа (стиральная машина/бойлер) | C97: шт | D97: 150000 | E97: 250000 | F97: =ROUND(D97*(1+'Логика цен'!$B$3),-3) | G97: =ROUND(E97*(1+'Логика цен'!$B$3),-3) | H97: =ROUND(F97/(1+'Логика цен'!$B$9),-3) | I97: =ROUND(G97/(1+'Логика цен'!$B$9),-3) | J97: =ROUND(D97*(1+'Логика цен'!$B$3)*(1-'Логика цен'!$B$8),-3) | K97: =ROUND(E97*(1+'Логика цен'!$B$3)*(1-'Логика цен'!$B$8),-3) | L97: =ROUND(D97*'Логика цен'!$B$6,-3)
A98: 87 | B98: Замена помпы/шланга стиральной машины | C98: шт | D98: 150000 | E98: 250000 | F98: =ROUND(D98*(1+'Логика цен'!$B$3),-3) | G98: =ROUND(E98*(1+'Логика цен'!$B$3),-3) | H98: =ROUND(F98/(1+'Логика цен'!$B$9),-3) | I98: =ROUND(G98/(1+'Логика цен'!$B$9),-3) | J98: =ROUND(D98*(1+'Логика цен'!$B$3)*(1-'Логика цен'!$B$8),-3) | K98: =ROUND(E98*(1+'Логика цен'!$B$3)*(1-'Логика цен'!$B$8),-3) | L98: =ROUND(D98*'Логика цен'!$B$6,-3)
A99: 88 | B99: Чистка бойлера от накипи | C99: шт | D99: 200000 | E99: 350000 | F99: =ROUND(D99*(1+'Логика цен'!$B$3),-3) | G99: =ROUND(E99*(1+'Логика цен'!$B$3),-3) | H99: =ROUND(F99/(1+'Логика цен'!$B$9),-3) | I99: =ROUND(G99/(1+'Логика цен'!$B$9),-3) | J99: =ROUND(D99*(1+'Логика цен'!$B$3)*(1-'Логика цен'!$B$8),-3) | K99: =ROUND(E99*(1+'Логика цен'!$B$3)*(1-'Логика цен'!$B$8),-3) | L99: =ROUND(D99*'Логика цен'!$B$6,-3)
A100: 89 | B100: Ремонт духовки/плиты (электрика: ТЭН, конфорка) | C100: заявка | D100: 150000 | E100: 300000 | F100: =ROUND(D100*(1+'Логика цен'!$B$3),-3) | G100: =ROUND(E100*(1+'Логика цен'!$B$3),-3) | H100: =ROUND(F100/(1+'Логика цен'!$B$9),-3) | I100: =ROUND(G100/(1+'Логика цен'!$B$9),-3) | J100: =ROUND(D100*(1+'Логика цен'!$B$3)*(1-'Логика цен'!$B$8),-3) | K100: =ROUND(E100*(1+'Логика цен'!$B$3)*(1-'Логика цен'!$B$8),-3) | L100: =ROUND(D100*'Логика цен'!$B$6,-3) | M100: Газовые — не берём
A101: 90 | B101: Установка/замена варочной панели (электро) | C101: шт | D101: 150000 | E101: 250000 | F101: =ROUND(D101*(1+'Логика цен'!$B$3),-3) | G101: =ROUND(E101*(1+'Логика цен'!$B$3),-3) | H101: =ROUND(F101/(1+'Логика цен'!$B$9),-3) | I101: =ROUND(G101/(1+'Логика цен'!$B$9),-3) | J101: =ROUND(D101*(1+'Логика цен'!$B$3)*(1-'Логика цен'!$B$8),-3) | K101: =ROUND(E101*(1+'Логика цен'!$B$3)*(1-'Логика цен'!$B$8),-3) | L101: =ROUND(D101*'Логика цен'!$B$6,-3)
...

Sheet B2B абонентка
A1: B2B: АБОНЕНТСКАЯ МОДЕЛЬ — фикс в договоре, сверх лимита отдельной счёт-фактурой
A3: Механика: клиент платит фикс. сумму в месяц. Работы списываются из неё по подписным ценам («B2B разовая» − 10%). Осмотры входят. Всё сверх суммы — отдельная СФ по ценам «B2B разовая» (+30% к B2C, без скидки).
A5: Параметр | B5: Базовый | C5: Стандарт | D5: Про | F5: Комментарий
A6: Целевой клиент | B6: Небольшой офис, магазин | C6: Кафе, салон, средний офис | D6: Ресторан, гостиница, сеть
A7: АБОНЕНТСКАЯ СУММА в договоре, сум/мес | B7: 1500000 | C7: 3000000 | D7: 5000000 | F7: Жёлтое: твоя цена в договоре
A8: Средний чек заявки по B2C-прайсу, сум | B8: 200000 | C8: 220000 | D8: 250000 | F8: У Про выше: кондиционеры, вентиляция, сварка
A9: Плановых осмотров в месяц | B9: 1 | C9: 1 | D9: 2
A10: Осмотры (списываются из абонентки), сум/мес | B10: =B9*'Логика цен'!$B$7 | C10: =C9*'Логика цен'!$B$7 | D10: =D9*'Логика цен'!$B$7
A11: Остаток абонентки на заявки, сум/мес | B11: =B7-B10 | C11: =C7-C10 | D11: =D7-D10
A12: Подписной средний чек («B2B разовая» − 10%), сум | B12: =ROUND(B8*(1+'Логика цен'!$B$3)*(1-'Логика цен'!$B$8),-3) | C12: =ROUND(C8*(1+'Логика цен'!$B$3)*(1-'Логика цен'!$B$8),-3) | D12: =ROUND(D8*(1+'Логика цен'!$B$3)*(1-'Логика цен'!$B$8),-3)
A13: ПОКРЫВАЕТ ЗАЯВОК В МЕСЯЦ, шт ≈ | B13: =ROUND(B11/B12,0) | C13: =ROUND(C11/C12,0) | D13: =ROUND(D11/D12,0)
A14: Те же работы по разовым B2B-ценам, сум/мес | B14: =ROUND((B13*B8+B9*'Логика цен'!$B$7)*(1+'Логика цен'!$B$3),-4) | C14: =ROUND((C13*C8+C9*'Логика цен'!$B$7)*(1+'Логика цен'!$B$3),-4) | D14: =ROUND((D13*D8+D9*'Логика цен'!$B$7)*(1+'Логика цен'!$B$3),-4)
A15: Выгода клиента от абонентки, сум/мес | B15: =B14-B7 | C15: =C14-C7 | D15: =D14-D7
A16: Выгода клиента, % | B16: =(B14-B7)/B14 | C16: =(C14-C7)/C14 | D16: =(D14-D7)/D14
A18: УСЛОВИЯ ДОГОВОРА (проект):
A19: • Работы учитываются по подписным ценам = «B2B разовая» × (1 − скидка с листа «Логика цен», B8).
A20: • Всё СВЕРХ абонентской суммы — отдельная счёт-фактура в конце месяца по ценам «B2B разовая» (+30%).
A21: • Неиспользованный остаток не переносится. (Вариант для переговоров: переносится до 20% на следующий месяц.)
A22: • Материалы всегда отдельно: по чеку, закрываются той же СФ.
A23: • Время реакции: Базовый — в течение дня, Стандарт — 4 часа, Про — 2 часа.
A24: • Договор от 6 месяцев, оплата абонентки авансом до 5 числа.
A25: • Все суммы (абонентка, СФ сверх лимита) — конечные, с НДС; в СФ НДС 12% выделяется изнутри (лист «Логика цен», B9).
A27: РЕГЛАМЕНТ ПЛАНОВОГО ОСМОТРА (входит): сантехника на течи, протяжка контактов в щитке, замена перегоревших
A28: ламп (лампы клиента), чистка фильтров кондиционеров (в сезон), осмотр вентиляции, проверка дверей/окон/замков,
A29: мелкий крепёж, фотоотчёт о состоянии объекта.
